{"Antoine Vermette ": ["Ondrej Kase", "Josh Manson", "Chris Wagner", "Ondrej Kase", "Nick Ritchie"], "Logan Shaw ": ["Chris Wagner", "Derek Grant"], "Chris Wagner ": ["Antoine Vermette", "Josh Manson", "Corey Perry", "Antoine Vermette"], "Kevin Bieksa ": [], "Ondrej Kase ": ["Jakob Silfverberg", "Brandon Montour", "Derek Grant", "Nick Ritchie", "Derek Grant", "Josh Manson"], "Andrew Cogliano ": ["Corey Perry", "Josh Manson", "Ryan Getzlaf", "Jakob Silfverberg", "Antoine Vermette"], "Jaycob Megna ": [], "Kalle Kossila ": ["Logan Shaw", "Chris Wagner"], "Josh Manson ": [], "Cam Fowler ": [], "Jared Boll ": ["Brandon Montour", "Logan Shaw"], "Corey Perry ": ["Rickard Rakell", "Rickard Rakell", "Andrew Cogliano", "Derek Grant", "Rickard Rakell"], "Hampus Lindholm ": ["Chris Wagner", "Dennis Rasmussen", "Rickard Rakell", "Rickard Rakell", "Sami Vatanen"], "Derek Grant ": ["Francois Beauchemin", "Brandon Montour", "Ondrej Kase", "Nick Ritchie", "Andrew Cogliano"], "Nick Ritchie ": ["Jakob Silfverberg", "Hampus Lindholm"], "Jakob Silfverberg ": ["Andrew Cogliano", "Hampus Lindholm", "Derek Grant", "Chris Wagner", "Rickard Rakell", "Corey Perry", "Andrew Cogliano", "Josh Manson"], "Francois Beauchemin ": [], "Brandon Montour ": ["Andrew Cogliano", "Logan Shaw", "Kevin Bieksa", "Jakob Silfverberg", "Kalle Kossila", "Francois Beauchemin", "Ryan Getzlaf", "Corey Perry", "Rickard Rakell"], "Sami Vatanen ": ["Rickard Rakell"], "Patrick Eaves ": ["Josh Manson", "Ryan Getzlaf"], "Rickard Rakell ": ["Andrew Cogliano", "Cam Fowler", "Andrew Cogliano", "Ryan Getzlaf", "Corey Perry", "Brandon Montour", "Ryan Getzlaf", "Ryan Getzlaf", "Corey Perry", "Josh Manson", "Derek Grant"], "Dennis Rasmussen ": ["Jaycob Megna", "Kevin Bieksa"], "Ryan Getzlaf ": ["Corey Perry"]}