{"Tyler Seguin ": ["Devin Shore", "John Klingberg", "John Klingberg", "Jamie Benn", "Devin Shore", "Jamie Benn", "Jamie Benn", "John Klingberg", "Jamie Benn", "John Klingberg", "Mattias Janmark", "Esa Lindell", "Alexander Radulov", "Jamie Benn", "John Klingberg", "Alexander Radulov", "Alexander Radulov", "Mattias Janmark", "John Klingberg", "Alexander Radulov"], "Antoine Roussel ": ["John Klingberg", "Tyler Seguin", "Jamie Benn", "John Klingberg", "Tyler Pitlick"], "Devin Shore ": ["Tyler Seguin", "John Klingberg", "Esa Lindell"], "Martin Hanzal ": ["Mattias Janmark"], "Greg Pateryn ": [], "Brett Ritchie ": ["Tyler Seguin", "Jamie Benn"], "Jamie Benn ": ["Jason Spezza", "John Klingberg", "Tyler Seguin", "Alexander Radulov", "Stephen Johns", "John Klingberg", "Tyler Seguin", "Alexander Radulov", "Dan Hamhuis", "Alexander Radulov", "John Klingberg", "John Klingberg", "Alexander Radulov", "Alexander Radulov", "Mattias Janmark", "Alexander Radulov", "Antoine Roussel", "Alexander Radulov"], "Mattias Janmark ": ["Jason Spezza", "Brett Ritchie", "Alexander Radulov", "Esa Lindell", "Devin Shore", "Stephen Johns", "Gemel Smith", "Tyler Seguin", "John Klingberg"], "John Klingberg ": ["Alexander Radulov", "Devin Shore", "Jason Spezza", "Jamie Benn", "Jamie Benn", "Tyler Seguin"], "Jamie Oleksiak ": [], "Tyler Pitlick ": ["Radek Faksa", "Dan Hamhuis", "Antoine Roussel", "Radek Faksa"], "Gemel Smith ": ["Alexander Radulov", "John Klingberg", "Brett Ritchie"], "Esa Lindell ": ["Devin Shore", "Stephen Johns", "Jason Spezza", "Dan Hamhuis", "Jason Spezza", "Mattias Janmark", "John Klingberg", "Martin Hanzal"], "Ben Bishop ": [], "Jason Spezza ": ["Esa Lindell", "Dan Hamhuis", "Ben Bishop", "Tyler Seguin", "Devin Shore"], "Dan Hamhuis ": ["Tyler Pitlick", "Radek Faksa"], "Radek Faksa ": ["Mattias Janmark", "Tyler Pitlick", "Gemel Smith", "John Klingberg", "Tyler Pitlick", "Jamie Oleksiak", "Dan Hamhuis", "Greg Pateryn", "Gemel Smith", "Brett Ritchie", "Antoine Roussel", "Tyler Pitlick"], "Alexander Radulov ": ["Tyler Seguin", "Dan Hamhuis", "Tyler Seguin", "Devin Shore", "Devin Shore", "John Klingberg", "Mattias Janmark", "Tyler Seguin", "Tyler Seguin", "Jamie Benn", "Antoine Roussel", "Esa Lindell", "Devin Shore"], "Remi Elie ": ["Antoine Roussel", "Jason Spezza", "Martin Hanzal", "Radek Faksa", "Tyler Pitlick"], "Stephen Johns ": ["Gemel Smith", "Radek Faksa"]}